keymaster_client/__init__.py
keymaster_client/cli.py
keymaster_client/config_scheme.py
keymaster_client/config_source.py
keymaster_client/keymaster_client.py
keymaster_client/wireguard.py
keymaster_client-1.0.3.dist-info/LICENSE
keymaster_client-1.0.3.dist-info/METADATA
keymaster_client-1.0.3.dist-info/WHEEL
keymaster_client-1.0.3.dist-info/entry_points.txt
keymaster_client-1.0.3.dist-info/top_level.txt
keymaster_client-1.0.3.dist-info/RECORD
