Metadata-Version: 2.1
Name: keymaster-client
Version: 1.0.3
Summary: Configures wireguard using information received from keymaster-server
Home-page: https://github.com/telus/keymaster-client
Author: Adam Pickering
Author-email: adamkpickering@gmail.com
License: BSD-3-Clause
Keywords: keymaster_client keymaster_server keymaster client server wireguard wire guard
Platform: UNKNOWN
Classifier: Development Status :: 3 - Alpha
Classifier: Intended Audience :: Developers
Classifier: License :: OSI Approved :: BSD License
Classifier: Natural Language :: English
Classifier: Programming Language :: Python :: 3
Classifier: Programming Language :: Python :: 3.8
Requires-Python: >=3.8
Requires-Dist: requests
Requires-Dist: click
Requires-Dist: pyyaml
